sentinelhub_downloader/__init__.py
sentinelhub_downloader/api.py
sentinelhub_downloader/cli.py
sentinelhub_downloader/config.py
sentinelhub_downloader/utils.py
sentinelhub_downloader/api/__init__.py
sentinelhub_downloader/api/byoc.py
sentinelhub_downloader/api/catalog.py
sentinelhub_downloader/api/client.py
sentinelhub_downloader/api/downloader.py
sentinelhub_downloader/api/main.py
sentinelhub_downloader/api/metadata.py
sentinelhub_downloader/api/process.py
sh_downloader-0.2.1.dist-info/LICENSE
sh_downloader-0.2.1.dist-info/METADATA
sh_downloader-0.2.1.dist-info/WHEEL
sh_downloader-0.2.1.dist-info/entry_points.txt
sh_downloader-0.2.1.dist-info/top_level.txt
sh_downloader-0.2.1.dist-info/RECORD
