Metadata-Version: 2.2
Name: sh-downloader
Version: 0.2.1
Summary: A command-line tool to download collections from Sentinel Hub as GeoTIFF's
Author-email: Chris Holmes <cholmes@planet.com>
License: MIT
Project-URL: Homepage, https://github.com/cholmes/sh-downloader
Project-URL: Bug Tracker, https://github.com/cholmes/sh-downloader/issues
Classifier: Programming Language :: Python :: 3
Classifier: Programming Language :: Python :: 3.8
Classifier: Programming Language :: Python :: 3.9
Classifier: Programming Language :: Python :: 3.10
Classifier: License :: OSI Approved :: MIT License
Classifier: Operating System :: OS Independent
Classifier: Intended Audience :: Science/Research
Classifier: Topic :: Scientific/Engineering :: GIS
Requires-Python: >=3.8
License-File: LICENSE
Requires-Dist: click>=8.0.0
Requires-Dist: sentinelhub>=3.4.0
Requires-Dist: shapely>=1.8.0
Requires-Dist: geojson>=2.5.0
Requires-Dist: requests>=2.27.0
Requires-Dist: tqdm>=4.64.0
Requires-Dist: rasterio>=1.2.0
Requires-Dist: numpy>=1.20.0
Provides-Extra: dev
Requires-Dist: pytest>=7.0.0; extra == "dev"
Requires-Dist: black>=22.3.0; extra == "dev"
Requires-Dist: isort>=5.10.0; extra == "dev"
Requires-Dist: flake8>=4.0.0; extra == "dev"
Provides-Extra: gdal
Requires-Dist: gdal>=3.0.0; extra == "gdal"
